openxmllib/__init__.py
openxmllib/contenttypes.py
openxmllib/document.py
openxmllib/namespaces.py
openxmllib/presentation.py
openxmllib/shell.py
openxmllib/spreadsheet.py
openxmllib/utils.py
openxmllib/version.txt
openxmllib/wordprocessing.py
openxmllib-1.1.dist-info/DESCRIPTION.rst
openxmllib-1.1.dist-info/METADATA
openxmllib-1.1.dist-info/RECORD
openxmllib-1.1.dist-info/WHEEL
openxmllib-1.1.dist-info/entry_points.txt
openxmllib-1.1.dist-info/metadata.json
openxmllib-1.1.dist-info/top_level.txt
